gigq/__init__.py
gigq/cli.py
gigq/db_utils.py
gigq/job.py
gigq/job_queue.py
gigq/job_status.py
gigq/table_formatter.py
gigq/utils.py
gigq/worker.py
gigq/workflow.py
gigq-0.2.0.dist-info/licenses/LICENSE
gigq-0.2.0.dist-info/METADATA
gigq-0.2.0.dist-info/WHEEL
gigq-0.2.0.dist-info/entry_points.txt
gigq-0.2.0.dist-info/top_level.txt
gigq-0.2.0.dist-info/RECORD
