Metadata-Version: 2.4
Name: gigq
Version: 0.2.0
Summary: A lightweight job queue system with SQLite backend and zero dependencies
Author-email: GigQ Team <info@gigq.dev>
License: MIT License
Project-URL: Homepage, https://github.com/kpouianou/gigq
Project-URL: Documentation, https://gigq.github.io/gigq
Project-URL: Issues, https://github.com/kpouianou/gigq/issues
Classifier: Development Status :: 3 - Alpha
Classifier: Intended Audience :: Developers
Classifier: License :: OSI Approved :: MIT License
Classifier: Programming Language :: Python :: 3
Classifier: Programming Language :: Python :: 3.9
Classifier: Programming Language :: Python :: 3.10
Classifier: Programming Language :: Python :: 3.11
Classifier: Programming Language :: Python :: 3.12
Classifier: Programming Language :: Python :: 3.13
Requires-Python: >=3.9
License-File: LICENSE
Provides-Extra: examples
Requires-Dist: requests; extra == "examples"
Requires-Dist: pandas; extra == "examples"
Requires-Dist: schedule; extra == "examples"
Provides-Extra: docs
Requires-Dist: mkdocs-material; extra == "docs"
Requires-Dist: pymdown-extensions; extra == "docs"
Requires-Dist: mkdocstrings[python]; extra == "docs"
Requires-Dist: mkdocs-git-revision-date-localized-plugin; extra == "docs"
Requires-Dist: mkdocs-minify-plugin; extra == "docs"
Requires-Dist: mike; extra == "docs"
Provides-Extra: dev
Requires-Dist: pytest; extra == "dev"
Requires-Dist: black; extra == "dev"
Requires-Dist: coverage; extra == "dev"
Requires-Dist: mypy; extra == "dev"
Provides-Extra: all
Requires-Dist: gigq[dev,docs,examples]; extra == "all"
Dynamic: license-file
